{
	"configurations" : 
	[
		{
			"directories" : 
			[
				{
					"build" : ".",
					"hasInstallRule" : true,
					"jsonFile" : "directory-.-Debug-f8b939e61d5a55b9a0e0.json",
					"minimumCMakeVersion" : 
					{
						"string" : "3.16"
					},
					"projectIndex" : 0,
					"source" : ".",
					"targetIndexes" : 
					[
						0,
						1,
						2
					]
				}
			],
			"name" : "Debug",
			"projects" : 
			[
				{
					"directoryIndexes" : 
					[
						0
					],
					"name" : "hello",
					"targetIndexes" : 
					[
						0,
						1,
						2
					]
				}
			],
			"targets" : 
			[
				{
					"directoryIndex" : 0,
					"id" : "hello::@6890427a1f51a3e7e1df",
					"jsonFile" : "target-hello-Debug-0716a0b8ddd6e1cb60f6.json",
					"name" : "hello",
					"projectIndex" : 0
				},
				{
					"directoryIndex" : 0,
					"id" : "hello_autogen::@6890427a1f51a3e7e1df",
					"jsonFile" : "target-hello_autogen-Debug-db5cb53a5f24b2b5ea0f.json",
					"name" : "hello_autogen",
					"projectIndex" : 0
				},
				{
					"directoryIndex" : 0,
					"id" : "hello_autogen_timestamp_deps::@6890427a1f51a3e7e1df",
					"jsonFile" : "target-hello_autogen_timestamp_deps-Debug-7f3164ceb29358eda77d.json",
					"name" : "hello_autogen_timestamp_deps",
					"projectIndex" : 0
				}
			]
		}
	],
	"kind" : "codemodel",
	"paths" : 
	{
		"build" : "/home/iot18/qt-project/hello/build/Desktop-Debug",
		"source" : "/home/iot18/qt-project/hello"
	},
	"version" : 
	{
		"major" : 2,
		"minor" : 6
	}
}
